[
  {
    "image": "images/festival/balloons.jpg",
    "country": "アメリカ",
    "title": "バルーンフェスタ",
    "outline": "ニューメキシコ州最大の街「アルパカーキ」の空をさまざまな形と色とりどりの気球で埋め尽くす圧巻の祭典。",
    "date": "毎年10月第一土曜日から9日間",
    "link": "#",
    "update": "2022-01-01"
  },
  {
    "image": "images/festival/chiang-mai.jpg",
    "country": "タイ",
    "title": "コムローイ",
    "outline": "夜空に和紙製のランタン（天燈）を放ち、天にいるブッダに感謝の気持ちを捧げる祭り。",
    "date": "2023年11月27日～28日",
    "link": "#",
    "update": "2022-01-01"
  },
  {
    "image": "images/festival/holi.jpg",
    "country": "インド",
    "title": "ホーリー祭",
    "outline": "色粉や色水を掛け合う祭り。人家に押し入ってくる悪鬼ビシャーチャを追い払うため泥や汚物を投げつけたのが始まりとされる。",
    "date": "2024年3月25日",
    "link": "#",
    "update": "2022-01-01"
  },
  {
    "image": "images/festival/lanthanum.jpg",
    "country": "ベトナム",
    "title": "ランタン祭り",
    "outline": "ランタン祭りは仏教行事を起源とし、新年や満月の夜にランタンを上げて無病息災を祈ったり、花火を打ち上げて邪気払いをすることからはじまっている。",
    "date": "2023年8月29日",
    "link": "#",
    "update": "2022-01-01"
  },
  {
    "image": "images/festival/rio-carnival.jpg",
    "country": "ブラジル",
    "title": "リオのカーニバル",
    "outline": "イースターに向けての禁欲期間へ入る直前に歌い踊り大騒ぎをして「食べ収め」をするという習俗に基づくキリスト教圏のお祭り。",
    "date": " 毎年2月～3月初めの土曜日から火曜日までの4日間",
    "link": "#",
    "update": "2022-01-01"
  },
  {
    "image": "images/festival/tomatoes.jpg",
    "country": "スペイン",
    "title": "ラ・トマティーナ",
    "outline": "若者が喧嘩でトマトを投げ合ったことが起源とされ、次の年にも同じメンバーがトマトを投げ合い、毎年行われるようになったという。",
    "date": "2023年8月30日",
    "link": "#",
    "update": "2022-01-01"
  }
]